modelark/__init__.py
modelark/common/__init__.py
modelark/common/context.py
modelark/common/editor.py
modelark/common/entity.py
modelark/common/locator.py
modelark/common/types.py
modelark/connector/__init__.py
modelark/connector/connection.py
modelark/connector/connector.py
modelark/filterer/__init__.py
modelark/filterer/function_parser.py
modelark/filterer/safe_eval.py
modelark/filterer/sql_parser.py
modelark/filterer/types.py
modelark/repository/__init__.py
modelark/repository/interface.py
modelark/repository/json_repository.py
modelark/repository/memory_repository.py
modelark/repository/repository.py
modelark/repository/repository_resolver.py
modelark/repository/rest_repository.py
modelark/repository/sql_repository.py
modelark-0.6.6.dist-info/LICENSE
modelark-0.6.6.dist-info/WHEEL
modelark-0.6.6.dist-info/METADATA
modelark-0.6.6.dist-info/RECORD
