Metadata-Version: 2.1
Name: modelark
Version: 0.6.6
Summary: Models Definition and Management Library
License: MIT
Author: Knowark
Requires-Python: >=3.8,<4.0
Classifier: License :: OSI Approved :: MIT License
Classifier: Programming Language :: Python :: 3
Classifier: Programming Language :: Python :: 3.8
Classifier: Programming Language :: Python :: 3.9
